{"stats":{"minecraft:mined":{"minecraft:sugar_cane":7},"minecraft:custom":{"minecraft:jump":1,"minecraft:open_chest":13,"minecraft:time_since_rest":4365,"minecraft:damage_taken":30,"minecraft:leave_game":2,"minecraft:play_time":4365,"minecraft:sprint_one_cm":4898,"minecraft:time_since_death":4365,"minecraft:walk_on_water_one_cm":476,"minecraft:walk_one_cm":38419,"minecraft:sneak_time":2,"minecraft:total_world_time":4365,"minecraft:fly_one_cm":10762,"minecraft:fall_one_cm":548,"minecraft:drop":26},"minecraft:crafted":{"minecraft:sugar":7},"minecraft:dropped":{"minecraft:cobbled_deepslate":1024,"minecraft:sugar_cane":4,"minecraft:sugar":7},"minecraft:picked_up":{"minecraft:sugar_cane":11}},"DataVersion":2724}